ragbits/chat/__init__.py
ragbits/chat/_utils.py
ragbits/chat/api.py
ragbits/chat/cli.py
ragbits/chat/metrics.py
ragbits/chat/py.typed
ragbits/chat/auth/__init__.py
ragbits/chat/auth/backends.py
ragbits/chat/auth/base.py
ragbits/chat/auth/types.py
ragbits/chat/client/__init__.py
ragbits/chat/client/client.py
ragbits/chat/client/conversation.py
ragbits/chat/client/exceptions.py
ragbits/chat/history/__init__.py
ragbits/chat/history/compressors/__init__.py
ragbits/chat/history/compressors/base.py
ragbits/chat/history/compressors/llm.py
ragbits/chat/interface/__init__.py
ragbits/chat/interface/_interface.py
ragbits/chat/interface/forms.py
ragbits/chat/interface/types.py
ragbits/chat/interface/ui_customization.py
ragbits/chat/persistence/__init__.py
ragbits/chat/persistence/base.py
ragbits/chat/persistence/file.py
ragbits/chat/persistence/sql.py
ragbits/chat/providers/__init__.py
ragbits/chat/providers/model_provider.py
ragbits/chat/ui-build/index.html
ragbits/chat/ui-build/assets/AuthGuard-B3JOY-uC.js
ragbits/chat/ui-build/assets/ChatHistory-D2Pd5V75.js
ragbits/chat/ui-build/assets/ChatOptionsForm-DYA6GEAP.js
ragbits/chat/ui-build/assets/FeedbackForm-Bovwe8ia.js
ragbits/chat/ui-build/assets/Login-B2kPNK-w.js
ragbits/chat/ui-build/assets/LogoutButton-Bspy5P1_.js
ragbits/chat/ui-build/assets/ShareButton-BvHR4xdz.js
ragbits/chat/ui-build/assets/UsageButton-BMDI2IGg.js
ragbits/chat/ui-build/assets/authStore-DLhLSjcY.js
ragbits/chat/ui-build/assets/chunk-IGSAU2ZA-DUS7ku-0.js
ragbits/chat/ui-build/assets/chunk-SSA7SXE4-DnKzYyYP.js
ragbits/chat/ui-build/assets/index-3BSSmhVm.js
ragbits/chat/ui-build/assets/index-BTHsSiyo.css
ragbits/chat/ui-build/assets/index-C75huGqt.js
ragbits/chat/ui-build/assets/index-I-Ja0wkh.js
ragbits/chat/ui-build/assets/index-VYICyW2P.js
ragbits_chat-1.3.0.dist-info/METADATA
ragbits_chat-1.3.0.dist-info/WHEEL
ragbits_chat-1.3.0.dist-info/RECORD
