Metadata-Version: 2.4
Name: ragbits-chat
Version: 1.3.0
Summary: Building blocks for rapid development of GenAI applications
Project-URL: Homepage, https://github.com/deepsense-ai/ragbits
Project-URL: Bug Reports, https://github.com/deepsense-ai/ragbits/issues
Project-URL: Documentation, https://ragbits.deepsense.ai/
Project-URL: Source, https://github.com/deepsense-ai/ragbits
Author-email: "deepsense.ai" <ragbits@deepsense.ai>
License-Expression: MIT
Keywords: GenAI,Generative AI,LLMs,Large Language Models,Prompt Management,RAG,Retrieval Augmented Generation
Classifier: Development Status :: 4 - Beta
Classifier: Environment :: Console
Classifier: Intended Audience :: Science/Research
Classifier: License :: OSI Approved :: MIT License
Classifier: Natural Language :: English
Classifier: Operating System :: OS Independent
Classifier: Programming Language :: Python :: 3.10
Classifier: Programming Language :: Python :: 3.11
Classifier: Programming Language :: Python :: 3.12
Classifier: Programming Language :: Python :: 3.13
Classifier: Topic :: Scientific/Engineering :: Artificial Intelligence
Classifier: Topic :: Software Development :: Libraries :: Python Modules
Requires-Python: >=3.10
Requires-Dist: bcrypt>=4.2.0
Requires-Dist: fastapi<1.0.0,>=0.115.0
Requires-Dist: httpx<1.0.0,>=0.28.1
Requires-Dist: python-jose[cryptography]>=3.5.0
Requires-Dist: ragbits-core==1.3.0
Requires-Dist: uvicorn<1.0.0,>=0.31.0
Provides-Extra: sql
Requires-Dist: sqlalchemy<3.0.0,>=2.0.39; extra == 'sql'
